apiEngine/__init__.py
apiEngine/_execute_case.py
apiEngine/global_tools.py
apiEngine/main.py
apiEngine/core/__init__.py
apiEngine/core/_basecase.py
apiEngine/core/_database_client.py
apiEngine/core/_test_result.py
apienginedivine-0.1.2.dist-info/licenses/LICENSE
apienginedivine-0.1.2.dist-info/METADATA
apienginedivine-0.1.2.dist-info/WHEEL
apienginedivine-0.1.2.dist-info/top_level.txt
apienginedivine-0.1.2.dist-info/RECORD
