Metadata-Version: 2.4
Name: apiEngineDivine
Version: 0.1.2
Summary: this is a api engine
Author: Divine
Author-email: 294491521@qq.com
Classifier: Programming Language :: Python :: 3
Classifier: License :: OSI Approved :: Apache Software License
Classifier: Operating System :: OS Independent
Requires-Python: >=3.11
License-File: LICENSE
Requires-Dist: requests>=2.31.0
Requires-Dist: jmespath>=0.10.0
Requires-Dist: jsonpath>=0.82.2
Requires-Dist: Faker>=38.2.0
Requires-Dist: PyMySQL>=1.1.2
Dynamic: author
Dynamic: author-email
Dynamic: classifier
Dynamic: description
Dynamic: description-content-type
Dynamic: license-file
Dynamic: requires-dist
Dynamic: requires-python
Dynamic: summary
